{
  "_class": "shapePath",
  "booleanOperation": 0,
  "clippingMaskMode": 0,
  "do_objectID": "1DC5D19C-A20D-40BB-8F89-FC479908AC15",
  "edited": true,
  "exportOptions": {
    "_class": "exportOptions",
    "do_objectID": "485CBD45-2620-46E6-B7EE-9AEBFD06A2F7",
    "exportFormats": [
    ],
    "includedLayerIds": [
    ],
    "layerOptions": 0,
    "shouldTrim": false
  },
  "frame": {
    "_class": "rect",
    "constrainProportions": false,
    "do_objectID": "CE380E66-73A1-40F9-B1C1-07F9C6204B41",
    "height": 11,
    "width": 8.107611989286882,
    "x": 5.946140653593051,
    "y": 0
  },
  "hasClippingMask": false,
  "isClosed": true,
  "isFixedToViewport": false,
  "isFlippedHorizontal": false,
  "isFlippedVertical": false,
  "isLocked": false,
  "isVisible": true,
  "layerListExpandedType": 0,
  "name": "Path",
  "nameIsFixed": false,
  "pointRadiusBehaviour": 1,
  "points": [
    {
      "_class": "curvePoint",
      "cornerRadius": 0,
      "curveFrom": "{0.22385762508460338, 4.0371746350005693e-17}",
      "curveMode": 2,
      "curveTo": "{0.77614237491539662, -4.0371746350005693e-17}",
      "hasCurveFrom": true,
      "hasCurveTo": true,
      "point": "{0.5, 0}"
    },
    {
      "_class": "curvePoint",
      "cornerRadius": 0,
      "curveFrom": "{0, 0.3636363636363637}",
      "curveMode": 4,
      "curveTo": "{0, 0.16280554551607523}",
      "hasCurveFrom": false,
      "hasCurveTo": true,
      "point": "{0, 0.3636363636363637}"
    },
    {
      "_class": "curvePoint",
      "cornerRadius": 0,
      "curveFrom": "{0, 0.8371944544839246}",
      "curveMode": 4,
      "curveTo": "{0, 0.63636363636363635}",
      "hasCurveFrom": true,
      "hasCurveTo": false,
      "point": "{0, 0.63636363636363635}"
    },
    {
      "_class": "curvePoint",
      "cornerRadius": 0,
      "curveFrom": "{0.77614237491539617, 1}",
      "curveMode": 2,
      "curveTo": "{0.22385762508460361, 1}",
      "hasCurveFrom": true,
      "hasCurveTo": true,
      "point": "{0.5, 1}"
    },
    {
      "_class": "curvePoint",
      "cornerRadius": 0,
      "curveFrom": "{1, 0.63636363636363635}",
      "curveMode": 4,
      "curveTo": "{1, 0.83719445448392449}",
      "hasCurveFrom": false,
      "hasCurveTo": true,
      "point": "{1, 0.63636363636363635}"
    },
    {
      "_class": "curvePoint",
      "cornerRadius": 0,
      "curveFrom": "{1, 0.16280554551607507}",
      "curveMode": 4,
      "curveTo": "{1, 0.36363636363636348}",
      "hasCurveFrom": true,
      "hasCurveTo": false,
      "point": "{1, 0.36363636363636348}"
    }
  ],
  "resizingConstraint": 63,
  "resizingType": 0,
  "rotation": 0,
  "shouldBreakMaskChain": false,
  "style": {
    "_class": "style",
    "borders": [
      {
        "_class": "border",
        "color": {
          "_class": "color",
          "alpha": 1,
          "blue": 1,
          "green": 1,
          "red": 1
        },
        "fillType": 0,
        "isEnabled": false,
        "position": 1,
        "thickness": 1.5
      }
    ],
    "do_objectID": "1BD5B4DA-043A-4517-AA5A-30A6B86BFC45",
    "endMarkerType": 0,
    "fills": [
      {
        "_class": "fill",
        "color": {
          "_class": "color",
          "alpha": 1,
          "blue": 1,
          "green": 0.4784313725490197,
          "red": 0
        },
        "fillType": 0,
        "isEnabled": true,
        "noiseIndex": 0,
        "noiseIntensity": 0,
        "patternFillType": 1,
        "patternTileScale": 1
      }
    ],
    "miterLimit": 10,
    "startMarkerType": 0,
    "windingRule": 1
  },
  "userInfo": {
    "com.animaapp.stc-sketch-plugin": {
      "kModelPropertiesKey": {
      }
    }
  }
}