{
  "_class": "symbolInstance",
  "booleanOperation": -1,
  "clippingMaskMode": 0,
  "do_objectID": "CBA0CD01-6654-437E-ACC0-749465380B3F",
  "exportOptions": {
    "_class": "exportOptions",
    "do_objectID": "2C8E812F-F950-4E57-B68B-7DCD7C1F9B15",
    "exportFormats": [
    ],
    "includedLayerIds": [
    ],
    "layerOptions": 0,
    "shouldTrim": false
  },
  "frame": {
    "_class": "rect",
    "constrainProportions": false,
    "do_objectID": "FD2B8D6B-DB01-415F-B7F8-B013BF1CFC89",
    "height": 24,
    "width": 24,
    "x": 744,
    "y": 427
  },
  "hasClippingMask": false,
  "horizontalSpacing": 0,
  "isFixedToViewport": false,
  "isFlippedHorizontal": false,
  "isFlippedVertical": false,
  "isLocked": false,
  "isVisible": true,
  "layerListExpandedType": 0,
  "name": "Glyph / Bill / Outlined Copy 43",
  "nameIsFixed": false,
  "overrideValues": [
  ],
  "resizingConstraint": 63,
  "resizingType": 0,
  "rotation": 0,
  "scale": 1,
  "shouldBreakMaskChain": true,
  "style": {
    "_class": "style",
    "do_objectID": "3CBFBB05-EE59-4A2B-A53F-2F1940834508",
    "endMarkerType": 0,
    "miterLimit": 10,
    "startMarkerType": 0,
    "windingRule": 1
  },
  "symbolID": "96F11DA4-6EA7-4B7B-B975-83CCCC099B1B",
  "verticalSpacing": 0
}