{
  "_class": "symbolInstance",
  "booleanOperation": -1,
  "clippingMaskMode": 0,
  "do_objectID": "F46821D5-C6AE-45A3-BC38-72F9DEE6E6DB",
  "exportOptions": {
    "_class": "exportOptions",
    "do_objectID": "B0779B1E-C2E9-4574-A8F1-26967F71DF29",
    "exportFormats": [
    ],
    "includedLayerIds": [
    ],
    "layerOptions": 0,
    "shouldTrim": false
  },
  "frame": {
    "_class": "rect",
    "constrainProportions": false,
    "do_objectID": "5D2FE649-B886-4B47-988C-B911EE2B2464",
    "height": 40,
    "width": 40,
    "x": 168,
    "y": 216
  },
  "hasClippingMask": false,
  "horizontalSpacing": 0,
  "isFixedToViewport": false,
  "isFlippedHorizontal": false,
  "isFlippedVertical": false,
  "isLocked": false,
  "isVisible": true,
  "layerListExpandedType": 0,
  "name": "Day26",
  "nameIsFixed": true,
  "overrideValues": [
  ],
  "resizingConstraint": 63,
  "resizingType": 0,
  "rotation": 0,
  "scale": 1,
  "shouldBreakMaskChain": false,
  "style": {
    "_class": "style",
    "do_objectID": "4021850F-58CE-4BA4-89EF-E16451696637",
    "endMarkerType": 0,
    "miterLimit": 10,
    "startMarkerType": 0,
    "windingRule": 1
  },
  "symbolID": "682FA8A3-AE97-48E7-BA2C-36F8C2D3C1E7",
  "verticalSpacing": 0
}