{
  "_class": "text",
  "attributedString": {
    "_class": "attributedString",
    "attributes": [
      {
        "_class": "stringAttribute",
        "attributes": {
          "MSAttributedStringColorAttribute": {
            "_class": "color",
            "alpha": 1,
            "blue": 0.400000006,
            "green": 0.400000006,
            "red": 0.400000006
          },
          "MSAttributedStringFontAttribute": {
            "_class": "fontDescriptor",
            "attributes": {
              "name": "TitilliumWeb-SemiBold",
              "size": 14
            }
          },
          "MSAttributedStringTextTransformAttribute": 1,
          "kerning": 1.75,
          "paragraphStyle": {
            "_class": "paragraphStyle",
            "alignment": 2,
            "allowsDefaultTighteningForTruncation": 0,
            "maximumLineHeight": 30,
            "minimumLineHeight": 30
          }
        },
        "length": 15,
        "location": 0
      }
    ],
    "string": "SERVICED STATES"
  },
  "automaticallyDrawOnUnderlyingPath": false,
  "booleanOperation": 0,
  "clippingMaskMode": 0,
  "do_objectID": "D927456C-82E0-4918-9E47-CA2B8895881E",
  "dontSynchroniseWithSymbol": false,
  "exportOptions": {
    "_class": "exportOptions",
    "do_objectID": "AE02E6FD-2112-402A-96E8-F1F42603BE43",
    "exportFormats": [
    ],
    "includedLayerIds": [
    ],
    "layerOptions": 0,
    "shouldTrim": false
  },
  "frame": {
    "_class": "rect",
    "constrainProportions": false,
    "do_objectID": "A34A1CB8-6AE5-440A-B8BF-8BBB91C01698",
    "height": 30,
    "width": 157,
    "x": 96,
    "y": 17
  },
  "glyphBounds": "{{11, 10}, {133, 11}}",
  "hasClippingMask": false,
  "isFixedToViewport": false,
  "isFlippedHorizontal": false,
  "isFlippedVertical": false,
  "isLocked": false,
  "isVisible": true,
  "layerListExpandedType": 0,
  "lineSpacingBehaviour": 2,
  "name": "SERVICED STATES",
  "nameIsFixed": false,
  "originalObjectID": "20EC6B7A-39A1-4996-8A97-AE65A57F1B71",
  "resizingConstraint": 47,
  "resizingType": 0,
  "rotation": 0,
  "sharedStyleID": "99185165-7C1D-4F06-9241-494A300F77E4",
  "shouldBreakMaskChain": false,
  "style": {
    "_class": "style",
    "do_objectID": "AFFBBC98-4C7A-422A-A929-D690836CA427",
    "endMarkerType": 0,
    "miterLimit": 10,
    "startMarkerType": 0,
    "textStyle": {
      "_class": "textStyle",
      "do_objectID": "383D2DAD-DC0D-4A9C-8045-388DE2C5E9CE",
      "encodedAttributes": {
        "MSAttributedStringColorAttribute": {
          "_class": "color",
          "alpha": 1,
          "blue": 0.400000006,
          "green": 0.400000006,
          "red": 0.400000006
        },
        "MSAttributedStringFontAttribute": {
          "_class": "fontDescriptor",
          "attributes": {
            "name": "TitilliumWeb-SemiBold",
            "size": 14
          }
        },
        "MSAttributedStringTextTransformAttribute": 1,
        "kerning": 1.75,
        "paragraphStyle": {
          "_class": "paragraphStyle",
          "alignment": 2,
          "allowsDefaultTighteningForTruncation": 0,
          "maximumLineHeight": 30,
          "minimumLineHeight": 30
        }
      },
      "verticalAlignment": 0
    },
    "windingRule": 1
  },
  "textBehaviour": 1
}