{
  "_class": "group",
  "booleanOperation": 0,
  "clippingMaskMode": 0,
  "do_objectID": "0876EEAD-E81B-4480-A28A-A0AFD89488E9",
  "exportOptions": {
    "_class": "exportOptions",
    "do_objectID": "98272226-09E4-4748-9FB8-74D7FDD71E7C",
    "exportFormats": [
    ],
    "includedLayerIds": [
    ],
    "layerOptions": 0,
    "shouldTrim": false
  },
  "frame": {
    "_class": "rect",
    "constrainProportions": false,
    "do_objectID": "A777BADC-8097-41CC-B946-BBC6602F303C",
    "height": 347,
    "width": 348,
    "x": 0,
    "y": 0
  },
  "hasClickThrough": false,
  "hasClippingMask": false,
  "isFixedToViewport": false,
  "isFlippedHorizontal": false,
  "isFlippedVertical": false,
  "isLocked": false,
  "isVisible": true,
  "layerListExpandedType": 1,
  "layers": [
    {
      "class": "shapePath",
      "id": "7611B129-E29A-45D0-A048-ADD8317798E3"
    },
    {
      "class": "shapePath",
      "id": "57C8BBC3-E2DC-4AA8-88DC-4DCA1193857C"
    },
    {
      "class": "shapePath",
      "id": "C97E6CC0-49F4-4CC1-8FCB-1D4AD66B93AD"
    },
    {
      "class": "shapePath",
      "id": "1A00422D-3419-4B53-B61F-2EA9625F2C5D"
    },
    {
      "class": "shapePath",
      "id": "C297B455-5369-4455-8696-2DC9CE15F738"
    },
    {
      "class": "shapePath",
      "id": "ADE44E3C-0A0B-4AE8-9FAD-71AFE6E32305"
    }
  ],
  "name": "Dividers",
  "nameIsFixed": true,
  "originalObjectID": "D53147A5-EDA0-407A-84B4-5D4C6462E2C7",
  "resizingConstraint": 63,
  "resizingType": 0,
  "rotation": 0,
  "shouldBreakMaskChain": false,
  "style": {
    "_class": "style",
    "do_objectID": "76C20064-5007-453D-809F-70910C5A7866",
    "endMarkerType": 0,
    "miterLimit": 10,
    "startMarkerType": 0,
    "windingRule": 1
  }
}