{
  "_class": "text",
  "attributedString": {
    "_class": "attributedString",
    "attributes": [
      {
        "_class": "stringAttribute",
        "attributes": {
          "MSAttributedStringColorAttribute": {
            "_class": "color",
            "alpha": 1,
            "blue": 1,
            "green": 1,
            "red": 1
          },
          "MSAttributedStringFontAttribute": {
            "_class": "fontDescriptor",
            "attributes": {
              "name": "TitilliumWeb-Bold",
              "size": 14
            }
          },
          "kerning": 1.75,
          "paragraphStyle": {
            "_class": "paragraphStyle",
            "alignment": 0,
            "allowsDefaultTighteningForTruncation": 0
          },
          "strikethroughStyle": 0,
          "underlineStyle": 0
        },
        "length": 9,
        "location": 0
      }
    ],
    "string": "ABOUT AGL"
  },
  "automaticallyDrawOnUnderlyingPath": false,
  "booleanOperation": -1,
  "clippingMaskMode": 0,
  "do_objectID": "56802771-A484-4725-9B77-58B541AC8C38",
  "dontSynchroniseWithSymbol": false,
  "exportOptions": {
    "_class": "exportOptions",
    "do_objectID": "E738A548-827A-4485-9782-B7A5E1BEDA43",
    "exportFormats": [
    ],
    "includedLayerIds": [
    ],
    "layerOptions": 0,
    "shouldTrim": false
  },
  "frame": {
    "_class": "rect",
    "constrainProportions": false,
    "do_objectID": "BD524E48-58F9-4B1F-A82D-D019E7182040",
    "height": 21,
    "width": 85,
    "x": 492,
    "y": 0
  },
  "glyphBounds": "{{0, 6}, {83, 11}}",
  "hasClippingMask": false,
  "isFixedToViewport": false,
  "isFlippedHorizontal": false,
  "isFlippedVertical": false,
  "isLocked": false,
  "isVisible": true,
  "layerListExpandedType": 0,
  "lineSpacingBehaviour": 2,
  "name": "ABOUT AGL",
  "nameIsFixed": false,
  "resizingConstraint": 47,
  "resizingType": 0,
  "rotation": 0,
  "sharedStyleID": "4B3765BC-2C40-4C5B-8E50-997349E4404D",
  "shouldBreakMaskChain": false,
  "style": {
    "_class": "style",
    "do_objectID": "5BB5D42C-12E4-45E3-A3C7-5FC5D7150645",
    "endMarkerType": 0,
    "miterLimit": 10,
    "shadows": [
      {
        "_class": "shadow",
        "blurRadius": 10,
        "color": {
          "_class": "color",
          "alpha": 0.5,
          "blue": 0,
          "green": 0,
          "red": 0
        },
        "contextSettings": {
          "_class": "graphicsContextSettings",
          "blendMode": 0,
          "opacity": 1
        },
        "isEnabled": false,
        "offsetX": 0,
        "offsetY": 2,
        "spread": 0
      }
    ],
    "startMarkerType": 0,
    "textStyle": {
      "_class": "textStyle",
      "do_objectID": "7C145D85-E11D-43E2-BD11-A13CD5945DDF",
      "encodedAttributes": {
        "MSAttributedStringColorAttribute": {
          "_class": "color",
          "alpha": 1,
          "blue": 1,
          "green": 1,
          "red": 1
        },
        "MSAttributedStringFontAttribute": {
          "_class": "fontDescriptor",
          "attributes": {
            "name": "TitilliumWeb-Bold",
            "size": 14
          }
        },
        "kerning": 1.75,
        "paragraphStyle": {
          "_class": "paragraphStyle",
          "alignment": 0,
          "allowsDefaultTighteningForTruncation": 0
        },
        "strikethroughStyle": 0,
        "underlineStyle": 0
      },
      "verticalAlignment": 1
    },
    "windingRule": 1
  },
  "textBehaviour": 0
}